MANIFEST.in
README.rst
setup.py
tastypie_mongodb/__init__.py
tastypie_mongodb/resources.py
tastypie_mongodb_resource.egg-info/PKG-INFO
tastypie_mongodb_resource.egg-info/SOURCES.txt
tastypie_mongodb_resource.egg-info/dependency_links.txt
tastypie_mongodb_resource.egg-info/not-zip-safe
tastypie_mongodb_resource.egg-info/requires.txt
tastypie_mongodb_resource.egg-info/top_level.txt