Metadata-Version: 1.1
Name: tastypie-mongodb-resource
Version: 0.0.6
Summary: Tastypie MongoDB Resource
Home-page: https://github.com/fatiherikli/tastypie-mongodb-resource
Author: Fatih Erikli
Author-email: fatiherikli@gmail.com
License: UNKNOWN
Keywords: tastypie rest api module resource mongodb
Platform: UNKNOWN
Classifier: Environment :: Console
Classifier: Environment :: Web Environment
Classifier: Framework :: Django
Classifier: Intended Audience :: Developers
Classifier: Natural Language :: English
Classifier: Programming Language :: Python
Classifier: Topic :: Internet
